05_latches_and_flipflops/T Flipflop/t_ff.v
module t_ff(
input t,clk,en,
output reg q
);

always @(posedge clk) begin
   if(en)
      q<=~t;
   else
      q<=q;

end

endmodule

05_latches_and_flipflops/T Flipflop/t_ff_tb.v
module t_ff_tb();
  reg en, t, clk;
  wire q;

  t_ff dut (.*);

  always #5 clk=~clk;

  initial begin

   $dumpfile("sim.vcd");
   $dumpvars(0,t_ff_tb);
   
    clk=0;
    #10; en=0; t=0;
    #10; en=1; t=0;  
    #10; en=1; t=1;   
    #10; en=0; t=0;   
    #10; en=1; t=1;   
    #10; en=0; t=0;
    #10; en=1; t=0;   
    #10; en=1; t=1;   
    #10; en=0; t=0;

    #10; $finish;
  end
 endmodule

05_latches_and_flipflops/T Flipflop/sim.vcd
$date
	Wed Sep  9 12:07:31 2026
$end
$version
	Icarus Verilog
$end
$timescale
	1s
$end
$scope module t_ff_tb $end
$var wire 1 ! q $end
$var reg 1 " clk $end
$var reg 1 # en $end
$var reg 1 $ t $end
$scope module dut $end
$var wire 1 " clk $end
$var wire 1 # en $end
$var wire 1 $ t $end
$var reg 1 ! q $end
$upscope $end
$upscope $end
$enddefinitions $end
$comment Show the parameter values. $end
$dumpall
$end
#0
$dumpvars
x$
x#
0"
x!
$end
#5
1"
#10
0"
0$
0#
#15
1"
#20
0"
1#
#25
1!
1"
#30
0"
1$
#35
0!
1"
#40
0"
0$
0#
#45
1"
#50
0"
1$
1#
#55
1"
#60
0"
0$
0#
#65
1"
#70
0"
1#
#75
1!
1"
#80
0"
1$
#85
0!
1"
#90
0"
0$
0#
