02_Basic_Combinational/011_Full_Subtractor/full_subtractor_gatelevel.v
module full_subtractor (

input a,b,c,
output sum,carry

);

wire c1,c2,c3,a1;



xor(sum,a,b,c);
not(a1,a);
and(c1, a1,b);
and(c2,b,c);
and(c3, a1, c);
or(carry, c1|c2|c3);



endmodule

02_Basic_Combinational/011_Full_Subtractor/full_subtractor_tb.v
module full_subtractor_tb();

reg a,b,c;
wire sum, carry;


full_subtractor uut(
.a(a),
.b(b),
.c(c),
.sum(sum),
.carry(carry)
);

initial begin 

$dumpfile("sim.vcd");
$dumpvars(0, uut);

$monitor("Time=%0t a=%b b=%b c=%b sum=%b carry= %b", $time, a, b, c, sum, carry);


a=0; b=0; c=0; #10;
a=0; b=0; c=1; #10; 
a=0; b=1; c=0; #10; 
a=0; b=1; c=1; #10; 
a=1; b=0; c=0; #10; 
a=1; b=0; c=1; #10; 
a=1; b=1; c=0; #10; 
a=1; b=1; c=1; #10;


$finish; 

end 
endmodule

02_Basic_Combinational/011_Full_Subtractor/sim.vcd
$date
	Tue Jun  9 21:24:01 2026
$end
$version
	Icarus Verilog
$end
$timescale
	1s
$end
$scope module full_subtractor_tb $end
$scope module uut $end
$var wire 1 ! a $end
$var wire 1 " a1 $end
$var wire 1 # b $end
$var wire 1 $ c $end
$var wire 1 % c1 $end
$var wire 1 & c2 $end
$var wire 1 ' c3 $end
$var wire 1 ( carry $end
$var wire 1 ) sum $end
$upscope $end
$upscope $end
$enddefinitions $end
$comment Show the parameter values. $end
$dumpall
$end
#0
$dumpvars
0)
0(
0'
0&
0%
0$
0#
1"
0!
$end
#10
1(
1)
1'
1$
#20
0'
1%
0$
1#
#30
0)
1&
1'
1$
#40
0(
0'
0%
0&
1)
0"
0$
0#
1!
#50
0)
1$
#60
0$
1#
#70
1(
1)
1&
1$
