01_Gates/006_XOR_GATE/gate_xor_dataflow.v
module gate_xor (
    input a,b,c,
    output y
);
    assign y= a^b^c;
endmodule

01_Gates/006_XOR_GATE/gate_xor_tb.v
module gate_xor_tb ();
    
reg a,b,c;
wire y;

gate_xor dut(
    .a(a),
    .b(b),
    .c(c),
    .y(y)
);

initial begin 

$dumpfile ("sim.vcd");
$dumpvars(0, dut);

$monitor("Time= %0t a=%b b=%b c=%c y=%b", $time, a,b,c,y);

a=0; b=0; c=0; #10;
a=0; b=0; c=1; #10;
a=0; b=1; c=0; #10;
a=0; b=1; c=1; #10;
a=1; b=0; c=0; #10;
a=1; b=0; c=1; #10;
a=1; b=1; c=0; #10;
a=1; b=1; c=1; #10;

$finish;

end
endmodule

01_Gates/006_XOR_GATE/sim.vcd
$date
	Thu Jun 04 12:42:43 2026
$end
$version
	Icarus Verilog
$end
$timescale
	1s
$end
$scope module gate_xor_tb $end
$scope module dut $end
$var wire 1 ! a $end
$var wire 1 " b $end
$var wire 1 # c $end
$var reg 1 $ y $end
$upscope $end
$upscope $end
$enddefinitions $end
$comment Show the parameter values. $end
$dumpall
$end
#0
$dumpvars
0$
0#
0"
0!
$end
#10
1$
1#
#20
0#
1"
#30
0$
1#
#40
1$
0#
0"
1!
#50
0$
1#
#60
0#
1"
#70
1$
1#
