02_Basic_Combinational/007_Full_adder/full_adder_behavioural.v
module full_adder (
    input a,b,c,
    output reg sum,carry
);
    always @(*) begin
        sum = (a^b^c);
        carry = ((a&b) | (b&c) | (c|a));
    end
endmodule

02_Combinational_circuits/01_Full_adder/Full_adder_behavioural/Using if_else/full_adder_tb.v
`timescale 1ps/1ps

module full_adder_tb();

reg a,b,c;
wire sum, carry;

full_adder dut(
    .a(a),
    .b(b),
    .c(c),
    .sum(sum),
    .carry(carry)
);

initial begin
    
    $dumpfile("sim.vcd");
    $dumpvars(0, dut);

    $monitor("Time= %0t a=%b b=%b c=%b sum=%b carry=%b", $time, a,b,c,sum,carry);

    a=0; b=0; c=0; #10;
    a=0; b=0; c=1; #10;
    a=0; b=1; c=0; #10;
    a=0; b=1; c=1; #10;
    a=1; b=0; c=0; #10;
    a=1; b=0; c=1; #10;
    a=1; b=1; c=0; #10;
    a=1; b=1; c=1; #10;

    $finish;


end





endmodule

02_Basic_Combinational/007_Full_adder/Full_adder_behavioural/Using if_else/sim.vcd
$date
	Tue Jun 09 09:37:53 2026
$end
$version
	Icarus Verilog
$end
$timescale
	1ps
$end
$scope module full_adder_tb $end
$scope module dut $end
$var wire 1 ! a $end
$var wire 1 " b $end
$var wire 1 # c $end
$var reg 1 $ carry $end
$var reg 1 % sum $end
$upscope $end
$upscope $end
$enddefinitions $end
$comment Show the parameter values. $end
$dumpall
$end
#0
$dumpvars
0%
0$
0#
0"
0!
$end
#10
1%
1#
#20
0#
1"
#30
1$
0%
1#
#40
0$
1%
0#
0"
1!
#50
1$
0%
1#
#60
0#
1"
#70
1%
1#
