02_Basic_Combinational/01_mux_2x1/mux_2x1_behavioural.v
module mux_2x1 (

input a,b,en,s,
output reg y

);

reg y1; 

always @ (*) begin


y1 = s ? b : a ;
y = y1 & en; 
	



end



endmodule

02_Combinational_circuits/06_Multiplexer/01_mux_2x1/mux_2x1_tb.v
module mux_2x1_tb ();

reg a,b,en,s;
wire y; 



mux_2x1 uut(

.a(a),
.b(b),
.en(en),
.s(s),
.y(y)

); 

initial begin

	$dumpfile ("sim.vcd");
	$dumpvars(0, uut);

	$monitor("Time = %0t a=%b b=%b en=%b s=%b y=%b ", $time,a,b,en,s,y);

	
	a=0; b=0; s=0; en=0;  #10; 
	a=0; b=1; s=0; en=1; #10;
	a=1; b=0; s=0; en=1; #10;
	a=1; b=1; s=0; en=1; #10;
	a=0; b=0; s=1; en=1; #10;
	a=0; b=1; s=1; en=1; #10;
	a=1; b=0; s=1; en=1; #10;
	a=1; b=1; s=1; en=1; #10;


	$finish; 





end







endmodule

02_Basic_Combinational/012_Multiplexer/01_mux_2x1/sim.vcd
$date
	Wed Jun 10 10:09:44 2026
$end
$version
	Icarus Verilog
$end
$timescale
	1s
$end
$scope module mux_2x1_tb $end
$scope module uut $end
$var wire 1 ! a $end
$var wire 1 " b $end
$var wire 1 # en $end
$var wire 1 $ s $end
$var reg 1 % y $end
$var reg 1 & y1 $end
$upscope $end
$upscope $end
$enddefinitions $end
$comment Show the parameter values. $end
$dumpall
$end
#0
$dumpvars
0&
0%
0$
0#
0"
0!
$end
#10
1#
1"
#20
1%
1&
0"
1!
#30
1"
#40
0%
0&
1$
0"
0!
#50
1%
1&
1"
#60
0%
0&
0"
1!
#70
1%
1&
1"
