02_Combinational_circuits/01_Full_adder/full_adder_gatelevel.v
module full_adder (
    input a,b,c,
    output sum,carry,o1,o2,o3
);

xor(sum,a,b,c);
and(o1,a,b);
and(o2,b,c);
and(o3,c,a);
or(carry,o1,o2,o3);
    
endmodule

02_Combinational_circuits/01_Full_adder/Full_adder_behavioural/Using if_else/full_adder_tb.v
`timescale 1ps/1ps

module full_adder_tb();

reg a,b,c;
wire sum, carry;

full_adder dut(
    .a(a),
    .b(b),
    .c(c),
    .sum(sum),
    .carry(carry)
);

initial begin
    
    $dumpfile("sim.vcd");
    $dumpvars(0, dut);

    $monitor("Time= %0t a=%b b=%b c=%b sum=%b carry=%b", $time, a,b,c,sum,carry);

    a=0; b=0; c=0; #10;
    a=0; b=0; c=1; #10;
    a=0; b=1; c=0; #10;
    a=0; b=1; c=1; #10;
    a=1; b=0; c=0; #10;
    a=1; b=0; c=1; #10;
    a=1; b=1; c=0; #10;
    a=1; b=1; c=1; #10;

    $finish;


end





endmodule

02_Combinational_circuits/01_Full_adder/sim.vcd
$date
	Fri Jun 05 09:23:37 2026
$end
$version
	Icarus Verilog
$end
$timescale
	1ps
$end
$scope module full_adder_tb $end
$scope module dut $end
$var wire 1 ! a $end
$var wire 1 " b $end
$var wire 1 # c $end
$var wire 1 $ carry $end
$var wire 1 % o1 $end
$var wire 1 & o2 $end
$var wire 1 ' o3 $end
$var wire 1 ( sum $end
$upscope $end
$upscope $end
$enddefinitions $end
$comment Show the parameter values. $end
$dumpall
$end
#0
$dumpvars
0(
0'
0&
0%
0$
0#
0"
0!
$end
#10
1(
1#
#20
0#
1"
#30
1$
0(
1&
1#
#40
0$
0&
1(
0#
0"
1!
#50
1$
0(
1'
1#
#60
0'
1%
0#
1"
#70
1(
1&
1'
1#
