05_latches_and_flipflops/JK FlipFlop/jk_ff.v
module jk_ff(
input j,k,clk,
output reg q
);

always @(posedge clk) begin

case({j,k})
2'b10:q=1'b1;
2'b01:q=1'b0;
2'b00:q=q;
2'b11:q=~q;
default:q=1'bx;
endcase

end

endmodule

05_latches_and_flipflops/JK FlipFlop/jk_ff_tb.v
module jk_ff_tb();
  reg j, k, clk;
  wire q;

  jk_ff dut (.*);

  always #5 clk=~clk;

  initial begin

   $dumpfile("sim.vcd");
   $dumpvars(0,jk_ff_tb);
   
    clk=0;
    #10; j=0; k=0;
    #10; j=1; k=0;  
    #10; j=0; k=1;   
    #10; j=0; k=0;   
    #10; j=1; k=1;   
    #10; j=0; k=0;
    #10; j=1; k=0;   
    #10; j=0; k=1;   
    #10; j=0; k=0;
    #10; j=1; k=1;

    #10; $finish;
  end
 endmodule

05_latches_and_flipflops/JK FlipFlop/sim.vcd
$date
	Wed Sep  9 12:04:19 2026
$end
$version
	Icarus Verilog
$end
$timescale
	1s
$end
$scope module jk_ff_tb $end
$var wire 1 ! q $end
$var reg 1 " clk $end
$var reg 1 # j $end
$var reg 1 $ k $end
$scope module dut $end
$var wire 1 " clk $end
$var wire 1 # j $end
$var wire 1 $ k $end
$var reg 1 ! q $end
$upscope $end
$upscope $end
$enddefinitions $end
$comment Show the parameter values. $end
$dumpall
$end
#0
$dumpvars
x$
x#
0"
x!
$end
#5
1"
#10
0"
0$
0#
#15
1"
#20
0"
1#
#25
1!
1"
#30
0"
1$
0#
#35
0!
1"
#40
0"
0$
#45
1"
#50
0"
1$
1#
#55
1!
1"
#60
0"
0$
0#
#65
1"
#70
0"
1#
#75
1"
#80
0"
1$
0#
#85
0!
1"
#90
0"
0$
#95
1"
#100
0"
1$
1#
#105
1!
1"
