02_Combinational_circuits/16_Basic_ALU/basic_alu.v
module basic_alu (

input [3:0] a,b, 
input [2:0] sel,
output reg [3:0] y,
output reg carry

); 

always @(*) begin

case (sel)



3'b000 : begin
{carry,y} = a+b;
end

3'b001 : begin
{carry,y} = a-b;
 end

3'b010 : begin
y = a&b;
 end

3'b011 : begin
y = a|b;
end

3'b100 : begin
y = a ^ b;
end

3'b101 : begin
y = ~a;
end

3'b110 : begin
y = a << 1; 
end

3'b111 : begin
y = a >> 1; 
end

default : begin

carry = 0;
y = 4'b0000;

end


endcase
end
endmodule

02_Combinational_circuits/16_Basic_ALU/tb_basic_alu.v
module tb_basic_alu();


reg [3:0] a;
reg [3:0] b;
reg [2:0] sel;
wire [3:0] y;
wire carry;


basic_alu uut(a,b,sel,y,carry); 

task apply_test; 

input [3:0] A,B;
input [2:0] Sel; 

begin 

a = A;
b = B;
sel = Sel;
#10;

$display ("A = %b , B = %b , Sel = %b ---> Y = %b , Carry = %b", a,b,sel,y,carry); 
end
endtask


initial begin

$dumpfile("sim.vcd");
$dumpvars(0,uut);

apply_test (4'd10, 4'd8, 3'd0);
apply_test (4'd11, 4'd2, 3'd1);
apply_test (4'd14, 4'd5, 3'd2);
apply_test (4'd8, 4'd3, 3'd3); 
apply_test (4'd3, 4'd8, 3'd4); 
apply_test (4'd5, 4'd9, 3'd5); 
apply_test (4'd5, 4'd5, 3'd6); 
apply_test (4'd9, 4'd11, 3'd7); 

end 




endmodule

02_Combinational_circuits/16_Basic_ALU/sim.vcd
$date
	Wed Jul  8 11:18:36 2026
$end
$version
	Icarus Verilog
$end
$timescale
	1s
$end
$scope module tb_basic_alu $end
$scope module uut $end
$var wire 4 ! a [3:0] $end
$var wire 4 " b [3:0] $end
$var wire 3 # sel [2:0] $end
$var reg 1 $ carry $end
$var reg 4 % y [3:0] $end
$upscope $end
$upscope $end
$enddefinitions $end
$comment Show the parameter values. $end
$dumpall
$end
#0
$dumpvars
b10 %
1$
b0 #
b1000 "
b1010 !
$end
#10
0$
b1001 %
b1 #
b10 "
b1011 !
#20
b100 %
b10 #
b101 "
b1110 !
#30
b1011 %
b11 #
b11 "
b1000 !
#40
b100 #
b1000 "
b11 !
#50
b1010 %
b101 #
b1001 "
b101 !
#60
b110 #
b101 "
#70
b100 %
b111 #
b1011 "
b1001 !
