02_Basic_Combinational/009_Full_adder_using_Half_adder/FA_using_HA_dataflow.v
module FA_using_HA (
    input a,b,c,
    output sum,carry
);

wire s1;
wire c1;
wire c2;

assign s1 = a^b;
assign c1 = a&b; 
assign c2 = s1&c;
assign sum = s1^c;
assign carry = c1 | c2;
    
endmodule

02_Basic_Combinational/009_Full_adder_using_Half_adder/FA_using_HA_tb.v
`timescale 1ps/1ps

module FA_using_HA_tb();

reg a,b,c;
wire sum, carry;

FA_using_HA dut (
    .a(a),
    .b(b),
    .c(c),
    .sum(sum),
    .carry(carry)
);

initial begin
    
    $dumpfile("sim.vcd");
    $dumpvars(0, dut);

    $monitor("Time= %0t a=%b b=%b c=%b sum=%b carry=%b", $time, a,b,c,sum,carry);

    a=0; b=0; c=0; #10;
    a=0; b=0; c=1; #10;
    a=0; b=1; c=0; #10;
    a=0; b=1; c=1; #10;
    a=1; b=0; c=0; #10;
    a=1; b=0; c=1; #10;
    a=1; b=1; c=0; #10;
    a=1; b=1; c=1; #10;

    $finish;


end





endmodule

02_Basic_Combinational/009_Full_adder_using_Half_adder/sim.vcd
$date
	Sat Jun 06 20:38:09 2026
$end
$version
	Icarus Verilog
$end
$timescale
	1ps
$end
$scope module FA_using_HA_tb $end
$scope module dut $end
$var wire 1 ! a $end
$var wire 1 " b $end
$var wire 1 # c $end
$var wire 1 $ c1 $end
$var wire 1 % c2 $end
$var wire 1 & carry $end
$var wire 1 ' s1 $end
$var wire 1 ( sum $end
$upscope $end
$upscope $end
$enddefinitions $end
$comment Show the parameter values. $end
$dumpall
$end
#0
$dumpvars
0(
0'
0&
0%
0$
0#
0"
0!
$end
#10
1(
1#
#20
1'
0#
1"
#30
0(
1#
#40
1(
0#
0"
1!
#50
0(
1#
#60
1&
0'
1$
0#
1"
#70
1(
1%
1#
