05_latches_and_flipflops/SR Flip Flop/sr_ff.v
module sr_ff(
input s,r,clk,
output reg q
);

always @(posedge clk) begin

case({s,r})
2'b10:q=1'b1;
2'b01:q=1'b0;
2'b00:q=q;
default:q=1'bx;
endcase

end

endmodule

05_latches_and_flipflops/SR Flip Flop/sr_ff_tb.v
module sr_ff_tb();
  reg s, r, clk;
  wire q;

  sr_ff dut (.*);

  always #5 clk=~clk;

  initial begin

   $dumpfile("sim.vcd");
   $dumpvars(0,sr_ff_tb);
   
    clk=0;
    #10; s=0; r=0;
    #10; s=1; r=0;  
    #10; s=0; r=1;   
    #10; s=0; r=0;   
    #10; s=1; r=1;   
    #10; s=0; r=0;
    #10; s=1; r=0;   
    #10; s=0; r=1;   
    #10; s=0; r=0;

    #10; $finish;
  end
 endmodule

05_latches_and_flipflops/SR Flip Flop/sim.vcd
$date
	Wed Sep  9 11:49:25 2026
$end
$version
	Icarus Verilog
$end
$timescale
	1s
$end
$scope module sr_ff_tb $end
$var wire 1 ! q $end
$var reg 1 " clk $end
$var reg 1 # r $end
$var reg 1 $ s $end
$scope module dut $end
$var wire 1 " clk $end
$var wire 1 # r $end
$var wire 1 $ s $end
$var reg 1 ! q $end
$upscope $end
$upscope $end
$enddefinitions $end
$comment Show the parameter values. $end
$dumpall
$end
#0
$dumpvars
x$
x#
0"
x!
$end
#5
1"
#10
0"
0#
0$
#15
1"
#20
0"
1$
#25
1!
1"
#30
0"
1#
0$
#35
0!
1"
#40
0"
0#
#45
1"
#50
0"
1#
1$
#55
x!
1"
#60
0"
0#
0$
#65
1"
#70
0"
1$
#75
1!
1"
#80
0"
1#
0$
#85
0!
1"
#90
0"
0#
