05_latches_and_flipflops/D Flip Flop/dff.v
module dff(
input d,clk,en,
output reg q
);

always @(posedge clk) begin
   if(en)
      q<=d;
   else
      q<=q;

end

endmodule

05_latches_and_flipflops/D Flip Flop/dff_tb.v
module dff_tb();
  reg en, d, clk;
  wire q;

  dff dut (.*);

  always #5 clk=~clk;

  initial begin

   $dumpfile("sim.vcd");
   $dumpvars(0,dff_tb);
   
    clk=0;
    #10; en=0; d=0;
    #10; en=1; d=0;  
    #10; en=1; d=1;   
    #10; en=0; d=0;   
    #10; en=1; d=1;   
    #10; en=0; d=0;
    #10; en=1; d=0;   
    #10; en=1; d=1;   
    #10; en=0; d=0;

    #10; $finish;
  end
 endmodule

05_latches_and_flipflops/D Flip Flop/sim.vcd
$date
	Wed Sep  9 12:00:48 2026
$end
$version
	Icarus Verilog
$end
$timescale
	1s
$end
$scope module dff_tb $end
$var wire 1 ! q $end
$var reg 1 " clk $end
$var reg 1 # d $end
$var reg 1 $ en $end
$scope module dut $end
$var wire 1 " clk $end
$var wire 1 # d $end
$var wire 1 $ en $end
$var reg 1 ! q $end
$upscope $end
$upscope $end
$enddefinitions $end
$comment Show the parameter values. $end
$dumpall
$end
#0
$dumpvars
x$
x#
0"
x!
$end
#5
1"
#10
0"
0#
0$
#15
1"
#20
0"
1$
#25
0!
1"
#30
0"
1#
#35
1!
1"
#40
0"
0#
0$
#45
1"
#50
0"
1#
1$
#55
1"
#60
0"
0#
0$
#65
1"
#70
0"
1$
#75
0!
1"
#80
0"
1#
#85
1!
1"
#90
0"
0#
0$
