02_Combinational_circuits/09_Encoder/02_encoder_8x3/encoder_8x3.v
module encoder_8x3(

output reg a,b,c,
input en, y7, y6, y5, y4, y3, y2, y1, y0

); 


always @(*) begin

if (!en) begin
a=0; b=0; c=0;
end

else begin

case ({y7, y6, y5, y4, y3, y2,y1, y0}) 

8'b00000001 : begin
a=0; b=0; c=0;  end


8'b00000010 : begin
a=0; b=0; c=1;  end

8'b00000100 : begin
a=0; b=1; c=0;  end


8'b00001000 : begin
a=0; b=1; c=1;  end


8'b00010000 : begin
a=1; b=0; c=0;  end


8'b00100000 : begin
a=1; b=0; c=1;  end

8'b01000000 : begin
a=1; b=1; c=0;  end


8'b10000000 : begin
a=1; b=1; c=1;  end

default : begin
a=0; b=0; c=0; end


endcase

end

end

endmodule

02_Basic_Combinational/015_Encoder/02_encoder_8x3/tb_encoder_8x3.v
module tb_encoder_8x3(); 

wire a, b, c;
reg en, y7, y6, y5, y4, y3, y2, y1, y0; 


encoder_8x3 uut(

 .en(en), 
 .a(a),
 .b(b),
 .c(c),
 .y7(y7),
 .y6(y6),
 .y5(y5),
 .y4(y4),
 .y3(y3),
 .y2(y2),
 .y1(y1),
 .y0(y0)
);


initial begin

$dumpfile ("sim.vcd");
$dumpvars(0, uut); 
$monitor("Time=%0t en=%b a=%b b=%b c=%b y7=%b y6=%b y5=%b y4=%b y3=%b y2=%b y1=%b y0=%b", $time, en,a,b,c,y7, y6, y5, y4, y3,y2,y1,y0);

#10; 
en = 0; y7=0; y6=0; y5=0; y4=0; y3=0; y2=0; y1=0; y0=0;  
#10;
en =1; y7=0; y6=0; y5=0; y4=0; y3=0; y2=0; y1=0; y0=1;
#10;
en =1; y7=0; y6=0; y5=0; y4=0; y3=0; y2=0; y1=1; y0=0;
#10;
en =1; y7=0; y6=0; y5=0; y4=0; y3=0; y2=1; y1=0; y0=0;
#10;
en =1; y7=0; y6=0; y5=0; y4=0; y3=1; y2=0; y1=0; y0=0;
#10;
en =1; y7=0; y6=0; y5=0; y4=1; y3=0; y2=0; y1=0; y0=0;
#10;
en =1; y7=0; y6=0; y5=1; y4=0; y3=0; y2=0; y1=0; y0=0;
#10;
en =1; y7=0; y6=1; y5=0; y4=0; y3=0; y2=0; y1=0; y0=0;
#10;
en =1; y7=1; y6=0; y5=0; y4=0; y3=0; y2=0; y1=0; y0=0;
#10



$finish; 

end




endmodule

02_Basic_Combinational/015_Encoder/02_encoder_8x3/sim.vcd
$date
	Wed Jul  1 19:02:45 2026
$end
$version
	Icarus Verilog
$end
$timescale
	1s
$end
$scope module tb_encoder_8x3 $end
$scope module uut $end
$var wire 1 ! en $end
$var wire 1 " y0 $end
$var wire 1 # y1 $end
$var wire 1 $ y2 $end
$var wire 1 % y3 $end
$var wire 1 & y4 $end
$var wire 1 ' y5 $end
$var wire 1 ( y6 $end
$var wire 1 ) y7 $end
$var reg 1 * a $end
$var reg 1 + b $end
$var reg 1 , c $end
$upscope $end
$upscope $end
$enddefinitions $end
$comment Show the parameter values. $end
$dumpall
$end
#0
$dumpvars
x,
x+
x*
x)
x(
x'
x&
x%
x$
x#
x"
x!
$end
#10
0,
0+
0*
0"
0#
0$
0%
0&
0'
0(
0)
0!
#20
1"
1!
#30
1,
0"
1#
#40
0,
1+
0#
1$
#50
1,
0$
1%
#60
0,
0+
1*
0%
1&
#70
1,
0&
1'
#80
0,
1+
0'
1(
#90
1,
0(
1)
