01_Gates/004_NAND_GATE/gate_nand_behavioural.v
module gate_nand (
    input a,b,c,
    output reg y
);
    always @(*) begin
        y = ~(a&b&c);
    end
endmodule

01_Gates/004_NAND_GATE/gate_nand_tb.v
module gate_nand_tb ();
    
    reg a,b,c;
    wire y;


 gate_nand uut(
    .a(a),
    .b(b),
    .c(c),
    .y(y)
 );

 initial begin 

 $dumpfile ("sim.vcd");
 $dumpvars(0, uut);

 $monitor("Time=%0t a=%b b=%b c=%b y=%b", $time, a, b, c, y);
 
 a=0; b=0; c=0; #10;
 a=0; b=0; c=1; #10;
 a=0; b=1; c=0; #10;
 a=0; b=1; c=1; #10;
 a=1; b=0; c=0; #10;
 a=1; b=0; c=1; #10;
 a=1; b=1; c=0; #10;
 a=1; b=1; c=1; #10;

 $finish;

 end

endmodule

01_Gates/004_NAND_GATE/sim.vcd
$date
	Wed Jun 03 17:19:52 2026
$end
$version
	Icarus Verilog
$end
$timescale
	1s
$end
$scope module gate_nand_tb $end
$scope module uut $end
$var wire 1 ! a $end
$var wire 1 " b $end
$var wire 1 # c $end
$var reg 1 $ y $end
$upscope $end
$upscope $end
$enddefinitions $end
$comment Show the parameter values. $end
$dumpall
$end
#0
$dumpvars
1$
0#
0"
0!
$end
#10
1#
#20
0#
1"
#30
1#
#40
0#
0"
1!
#50
1#
#60
0#
1"
#70
0$
1#
