02_Combinational_circuits/08_Decoder/02_decoder_3x8/decoder_3x8.v
module decoder_3x8 (

input en, a,b,c,
output reg y7, y6, y5, y4, y3, y2, y1, y0

); 


always @(*) begin

if (!en) begin
y7=0; y6=0; y5=0; y4=0; y3=0; y2=0; y1=0; y0=0;
end

else begin

case ({a,b,c}) 

3'b000 : begin
y7=0; y6=0; y5=0; y4=0; y3=0; y2=0; y1=0; y0=1; end

3'b001 : begin
y7=0; y6=0; y5=0; y4=0; y3=0; y2=0; y1=1; y0=0; end


3'b010 : begin
y7=0; y6=0; y5=0; y4=0; y3=0; y2=1; y1=0; y0=0; end

3'b011 : begin
y7=0; y6=0; y5=0; y4=0; y3=1; y2=0; y1=0; y0=0; end


3'b100 : begin
y7=0; y6=0; y5=0; y4=1; y3=0; y2=0; y1=0; y0=0; end


3'b101 : begin
y7=0; y6=0; y5=1; y4=0; y3=0; y2=0; y1=0; y0=0; end


3'b110 : begin
y7=0; y6=1; y5=0; y4=0; y3=0; y2=0; y1=0; y0=0; end


3'b111 : begin
y7=1; y6=0; y5=0; y4=0; y3=0; y2=0; y1=0; y0=0; end



endcase

end

end

endmodule

02_Basic_Combinational/014_Decoder/02_decoder_3x8/tb_decoder_3x8.v
module tb_decoder_3x8(); 

reg en, a, b, c;
wire y7, y6, y5, y4, y3, y2, y1, y0; 


decoder_3x8 uut(

 .en(en), 
 .a(a),
 .b(b),
 .c(c),
 .y7(y4),
 .y6(y6),
 .y5(y5),
 .y4(y4),
 .y3(y3),
 .y2(y2),
 .y1(y1),
 .y0(y0)
);


initial begin

$dumpfile ("sim.vcd");
$dumpvars(0, uut); 
$monitor("Time=%0t en=%b a=%b b=%b c=%b y7=%b y6=%b y5=%b y4=%b y3=%b y2=%b y1=%b y0=%b", $time, en,a,b,c,y7, y6, y5, y4, y3,y2,y1,y0);

#10; 
en = 0; a=0; b=0; c=0;  
#10;
en =1; a=0; b=0; c=0;
#10;
en =1; a=0; b=0; c=1;  
#10;
en=1; a=0; b=1; c=0;
#10; 
en=1; a=0; b=1; c=1;
#10;
en=1; a=1; b=0; c=0;
#10;
en=1; a=1; b=0; c=1;
#10;
en=1; a=1; b=1; c=0;
#10;
en=1; a=1; b=1; c=1;
#10;


$finish; 

end




endmodule

02_Basic_Combinational/014_Decoder/02_decoder_3x8/sim.vcd
$date
	Wed Jul  1 18:09:21 2026
$end
$version
	Icarus Verilog
$end
$timescale
	1s
$end
$scope module tb_decoder_3x8 $end
$scope module uut $end
$var wire 1 ! a $end
$var wire 1 " b $end
$var wire 1 # c $end
$var wire 1 $ en $end
$var reg 1 % y0 $end
$var reg 1 & y1 $end
$var reg 1 ' y2 $end
$var reg 1 ( y3 $end
$var reg 1 ) y4 $end
$var reg 1 * y5 $end
$var reg 1 + y6 $end
$var reg 1 , y7 $end
$upscope $end
$upscope $end
$enddefinitions $end
$comment Show the parameter values. $end
$dumpall
$end
#0
$dumpvars
x,
x+
x*
x)
x(
x'
x&
x%
x$
x#
x"
x!
$end
#10
0%
0&
0'
0(
0)
0*
0+
0,
0#
0"
0!
0$
#20
1%
1$
#30
0%
1&
1#
#40
0&
1'
0#
1"
#50
0'
1(
1#
#60
0(
1)
0#
0"
1!
#70
0)
1*
1#
#80
0*
1+
0#
1"
#90
0+
1,
1#
